jaxserve/__init__.py
jaxserve/py.typed
jaxserve-0.0.1.dev0.dist-info/METADATA
jaxserve-0.0.1.dev0.dist-info/WHEEL
jaxserve-0.0.1.dev0.dist-info/licenses/LICENSE
jaxserve-0.0.1.dev0.dist-info/RECORD
